knotctl/__init__.py
knotctl-0.1.1.dist-info/entry_points.txt
knotctl-0.1.1.dist-info/LICENSE
knotctl-0.1.1.dist-info/WHEEL
knotctl-0.1.1.dist-info/METADATA
knotctl-0.1.1.dist-info/RECORD
