Metadata-Version: 2.1
Name: knotctl
Version: 0.1.1
Summary: A CLI for knotapi.
Author-email: Micke Nordin <hej@mic.ke>
Requires-Python: >=3.9
Classifier: Programming Language :: Python :: 3
Classifier: License :: OSI Approved :: GNU General Public License v3 (GPLv3)
Classifier: Operating System :: OS Independent
Requires-Dist: argcomplete==2.0.0
Requires-Dist: pyyaml==6.0.1
Requires-Dist: requests==2.27.1
Requires-Dist: simplejson==3.17.6
Project-URL: Documentation, https://code.smolnet.org/micke/knotctl
Project-URL: Source, https://code.smolnet.org/micke/knotctl
